{"authority": false, "engine_id": "receiptos-replay-engine", "engine_version": "0.1", "errors": ["INV_COMMIT_RESOLVABLE"], "exit_code": 5, "input_hash": "cbad450a48acaf67c3630745dbc12ff482cd68e5f9e614891537b8f2fb93ff62", "output_hash": "a40faf330c6b0947e0a1b43adc2031caabdd6309461ad637922d8587114b8019", "receipt_type": "replay_run", "receipt_version": "0.1", "replay_invariants": ["INV_READ_ONLY_WORKSPACE", "INV_COMMIT_RESOLVABLE", "INV_TREE_HASH_MATCH", "INV_CANONICAL_SURFACES_PRESENT", "INV_DETERMINISTIC_OUTPUT"], "status": "FAIL", "timestamp": "2026-07-07T07:54:02Z"}
